corriente/__init__.py
corriente/version.py
corriente-0.1.dist-info/LICENSE
corriente-0.1.dist-info/METADATA
corriente-0.1.dist-info/WHEEL
corriente-0.1.dist-info/top_level.txt
corriente-0.1.dist-info/RECORD
