Metadata-Version: 2.1
Name: corriente
Version: 0.1
Summary: Python streaming library
Home-page: https://github.com/jadielam/corriente
Author: Jadiel de Armas
Author-email: jadielam@gmail.com
License: MIT
Platform: UNKNOWN
Classifier: License :: OSI Approved :: MIT License
Classifier: Programming Language :: Python
Classifier: Programming Language :: Python :: 2
Classifier: Programming Language :: Python :: 3
Requires-Dist: opencv-python
